vera_core/LICENSE
vera_core/__init__.py
vera_core/app/__init__.py
vera_core/app/jupyter.py
vera_core/app/main.py
vera_core/app/core/__init__.py
vera_core/app/core/vera_out_file.py
vera_core/app/ui/__init__.py
vera_core/app/ui/assembly_view.py
vera_core/app/ui/axial_plot.py
vera_core/app/ui/core_view.py
vera_core/app/ui/empty.py
vera_core/app/ui/table_view.py
vera_core/app/ui/time_plot.py
vera_core/app/ui/volume_view.py
vera_core/app/ui/x_axial_view.py
vera_core/app/ui/y_axial_view.py
vera_core/app/ui/assets/__init__.py
vera_core/app/ui/assets/logo.svg
vera_core/module/__init__.py
vera_core/module/serve/vue-vera_core.css
vera_core/module/serve/vue-vera_core.umd.min.js
vera_core/widgets/__init__.py
vera_core/widgets/vera.py
vera_core-1.3.1.dist-info/LICENSE
vera_core-1.3.1.dist-info/METADATA
vera_core-1.3.1.dist-info/WHEEL
vera_core-1.3.1.dist-info/entry_points.txt
vera_core-1.3.1.dist-info/top_level.txt
vera_core-1.3.1.dist-info/RECORD
