Metadata-Version: 2.1
Name: vera-core
Version: 1.3.1
Summary: VERACore let you visualize and interpret the output data from VERA codes
Author: Kitware Inc.
License: Apache Software License
Keywords: Python,Interactive,Web,Application,Framework
Classifier: Development Status :: 4 - Beta
Classifier: Environment :: Web Environment
Classifier: License :: OSI Approved :: Apache Software License
Classifier: Natural Language :: English
Classifier: Operating System :: OS Independent
Classifier: Programming Language :: Python :: 3 :: Only
Classifier: Programming Language :: JavaScript
Classifier: Topic :: Software Development :: Libraries :: Application Frameworks
Classifier: Topic :: Software Development :: Libraries :: Python Modules
License-File: LICENSE
Requires-Dist: trame >=3
Requires-Dist: trame-vtk
Requires-Dist: trame-vuetify
Requires-Dist: trame-plotly
Requires-Dist: trame-grid-layout
Requires-Dist: h5py
Requires-Dist: pandas
Requires-Dist: plotly
Requires-Dist: vtk
